rtl/rv32i_defs.vh
// rv32i_defs.vh — shared constants for the RV32I core
// Verilog-2001 header (include with `include "rv32i_defs.vh"`).
// Kept as localparam-style `define constants so leaf modules stay standalone.
`ifndef RV32I_DEFS_VH
`define RV32I_DEFS_VH

// ---- Opcodes (instr[6:0]) ----
`define OPC_LUI     7'b0110111
`define OPC_AUIPC   7'b0010111
`define OPC_JAL     7'b1101111
`define OPC_JALR    7'b1100111
`define OPC_BRANCH  7'b1100011
`define OPC_LOAD    7'b0000011
`define OPC_STORE   7'b0100011
`define OPC_OPIMM   7'b0010011
`define OPC_OP      7'b0110011
`define OPC_MISCMEM 7'b0001111  // FENCE (treated as NOP)
`define OPC_SYSTEM  7'b1110011  // ECALL/EBREAK (treated as HALT)

// ---- ALU operation select (alu_op) ----
`define ALU_ADD   4'd0
`define ALU_SUB   4'd1
`define ALU_SLL   4'd2
`define ALU_SLT   4'd3
`define ALU_SLTU  4'd4
`define ALU_XOR   4'd5
`define ALU_SRL   4'd6
`define ALU_SRA   4'd7
`define ALU_OR    4'd8
`define ALU_AND   4'd9
`define ALU_BSEL  4'd10  // pass operand B unchanged (for LUI)

// ---- Writeback result select (result_sel) ----
`define RES_ALU   2'b00
`define RES_MEM   2'b01
`define RES_PC4   2'b10  // PC+4 for JAL/JALR link

// ---- ALU operand-A select ----
`define A_RS1     1'b0
`define A_PC      1'b1   // for AUIPC

// ---- ALU operand-B select ----
`define B_RS2     1'b0
`define B_IMM     1'b1

// ---- funct3: branches ----
`define F3_BEQ    3'b000
`define F3_BNE    3'b001
`define F3_BLT    3'b100
`define F3_BGE    3'b101
`define F3_BLTU   3'b110
`define F3_BGEU   3'b111

// ---- funct3: loads/stores (width/sign) ----
`define F3_B      3'b000  // byte  (signed load)
`define F3_H      3'b001  // half  (signed load)
`define F3_W      3'b010  // word
`define F3_BU     3'b100  // byte  (unsigned load)
`define F3_HU     3'b101  // half  (unsigned load)

`endif // RV32I_DEFS_VH

rtl/dmem.v
// dmem.v — synchronous single-port data memory (infers BRAM).
// Word-addressed with per-byte write enables (for SB/SH/SW). One-cycle read
// latency: address presented in EX, data valid in MEM/WB. Read-first on a
// simultaneous R/W to the same word (only ever one memory op is in flight).
`default_nettype none

module dmem #(
    parameter ADDR_WIDTH = 12,
    parameter INIT_FILE  = ""
)(
    input  wire        clk,
    input  wire        en,
    input  wire [3:0]  we,              // per-byte write strobe
    input  wire [31:0] addr,            // byte address
    input  wire [31:0] wdata,           // pre-aligned (data replicated across lanes)
    output reg  [31:0] rdata
);
    localparam DEPTH = (1 << ADDR_WIDTH);
    (* ram_style = "block" *)
    reg [31:0] mem [0:DEPTH-1];

    wire [ADDR_WIDTH-1:0] widx = addr[ADDR_WIDTH+1:2];

    integer i;
    initial begin
        for (i = 0; i < DEPTH; i = i + 1)
            mem[i] = 32'h0000_0000;
        if (INIT_FILE != "")
            $readmemh(INIT_FILE, mem);
    end

    always @(posedge clk) begin
        if (en) begin
            if (we[0]) mem[widx][7:0]   <= wdata[7:0];
            if (we[1]) mem[widx][15:8]  <= wdata[15:8];
            if (we[2]) mem[widx][23:16] <= wdata[23:16];
            if (we[3]) mem[widx][31:24] <= wdata[31:24];
            rdata <= mem[widx];         // read-first
        end
    end
endmodule

`default_nettype wire

rtl/alu.v
// alu.v — RV32I arithmetic/logic unit (pure combinational).
// One 4-bit op select drives all base-integer datapath operations.
`include "rv32i_defs.vh"
`default_nettype none

module alu (
    input  wire [31:0] a,
    input  wire [31:0] b,
    input  wire [3:0]  op,
    output reg  [31:0] y,
    output wire        zero    // y == 0, handy for reuse
);
    // Shift amount is the low 5 bits of b (RV32I: SLL/SRL/SRA by reg or imm).
    wire [4:0] shamt = b[4:0];

    always @(*) begin
        case (op)
            `ALU_ADD : y = a + b;
            `ALU_SUB : y = a - b;
            `ALU_SLL : y = a << shamt;
            `ALU_SLT : y = ($signed(a) < $signed(b)) ? 32'd1 : 32'd0;
            `ALU_SLTU: y = (a < b) ? 32'd1 : 32'd0;
            `ALU_XOR : y = a ^ b;
            `ALU_SRL : y = a >> shamt;
            `ALU_SRA : y = $signed(a) >>> shamt;
            `ALU_OR  : y = a | b;
            `ALU_AND : y = a & b;
            `ALU_BSEL: y = b;               // LUI: forward the U-immediate
            default  : y = 32'd0;           // safe default, avoids latch
        endcase
    end

    assign zero = (y == 32'd0);
endmodule

`default_nettype wire

rtl/regfile.v
// regfile.v — 32x32 RV32I register file.
// Two combinational read ports, one synchronous write port.
// x0 is hardwired to zero (writes to it are ignored).
// Read-during-write returns the OLD value (write commits on the clock edge);
// the pipeline covers the same-cycle case with WB->EX forwarding upstream.
`default_nettype none

module regfile (
    input  wire        clk,
    // read port 1
    input  wire [4:0]  rs1_addr,
    output wire [31:0] rs1_data,
    // read port 2
    input  wire [4:0]  rs2_addr,
    output wire [31:0] rs2_data,
    // write port
    input  wire        we,
    input  wire [4:0]  rd_addr,
    input  wire [31:0] rd_data
);
    reg [31:0] xreg [1:31];   // x0 not stored; it is a constant zero

    // Combinational reads; x0 forced to zero.
    assign rs1_data = (rs1_addr == 5'd0) ? 32'd0 : xreg[rs1_addr];
    assign rs2_data = (rs2_addr == 5'd0) ? 32'd0 : xreg[rs2_addr];

    always @(posedge clk) begin
        if (we && (rd_addr != 5'd0))
            xreg[rd_addr] <= rd_data;
    end
endmodule

`default_nettype wire

rtl/decoder.v
// decoder.v — RV32I instruction decoder (pure combinational).
// Cracks a 32-bit instruction into register addresses, a sign-extended
// immediate, and the datapath control word consumed by the EX stage.
// Illegal/unknown opcodes decode to a NOP (no arch state change).
`include "rv32i_defs.vh"
`default_nettype none

module decoder (
    input  wire [31:0] instr,

    output wire [4:0]  rs1,
    output wire [4:0]  rs2,
    output wire [4:0]  rd,
    output wire [2:0]  funct3,

    output reg  [31:0] imm,
    output reg  [3:0]  alu_op,
    output reg         alu_src_a,   // A_RS1 / A_PC
    output reg         alu_src_b,   // B_RS2 / B_IMM
    output reg  [1:0]  result_sel,  // RES_ALU / RES_MEM / RES_PC4
    output reg         reg_write,
    output reg         mem_read,
    output reg         mem_write,
    output reg         is_branch,
    output reg         is_jal,
    output reg         is_jalr,
    output reg         is_halt      // ECALL/EBREAK -> stop the CPU
);
    wire [6:0] opcode = instr[6:0];
    wire [6:0] funct7 = instr[31:25];

    assign rs1    = instr[19:15];
    assign rs2    = instr[24:20];
    assign rd     = instr[11:7];
    assign funct3 = instr[14:12];

    // ---- Immediate variants (RV32I) ----
    wire [31:0] imm_i = {{20{instr[31]}}, instr[31:20]};
    wire [31:0] imm_s = {{20{instr[31]}}, instr[31:25], instr[11:7]};
    wire [31:0] imm_b = {{19{instr[31]}}, instr[31], instr[7],
                         instr[30:25], instr[11:8], 1'b0};
    wire [31:0] imm_u = {instr[31:12], 12'b0};
    wire [31:0] imm_j = {{11{instr[31]}}, instr[31], instr[19:12],
                         instr[20], instr[30:21], 1'b0};

    // ---- ALU op for OP / OP-IMM from funct3 (+ funct7[5] for SUB/SRA) ----
    // instr[30] selects SUB (from ADD) and SRA (from SRL). For OP-IMM only
    // the shift-right form (funct3==101) consults instr[30]; ADDI never subs.
    reg [3:0] alu_op_arith;
    always @(*) begin
        case (funct3)
            3'b000: alu_op_arith = (opcode == `OPC_OP && instr[30]) ? `ALU_SUB : `ALU_ADD;
            3'b001: alu_op_arith = `ALU_SLL;
            3'b010: alu_op_arith = `ALU_SLT;
            3'b011: alu_op_arith = `ALU_SLTU;
            3'b100: alu_op_arith = `ALU_XOR;
            3'b101: alu_op_arith = instr[30] ? `ALU_SRA : `ALU_SRL;
            3'b110: alu_op_arith = `ALU_OR;
            3'b111: alu_op_arith = `ALU_AND;
            default: alu_op_arith = `ALU_ADD;
        endcase
    end

    always @(*) begin
        // Safe NOP defaults (prevents latch inference; unknown opcodes are NOPs).
        imm        = 32'd0;
        alu_op     = `ALU_ADD;
        alu_src_a  = `A_RS1;
        alu_src_b  = `B_IMM;
        result_sel = `RES_ALU;
        reg_write  = 1'b0;
        mem_read   = 1'b0;
        mem_write  = 1'b0;
        is_branch  = 1'b0;
        is_jal     = 1'b0;
        is_jalr    = 1'b0;
        is_halt    = 1'b0;

        case (opcode)
            `OPC_LUI: begin
                imm = imm_u; alu_op = `ALU_BSEL; alu_src_b = `B_IMM;
                reg_write = 1'b1;
            end
            `OPC_AUIPC: begin
                imm = imm_u; alu_op = `ALU_ADD;
                alu_src_a = `A_PC; alu_src_b = `B_IMM;
                reg_write = 1'b1;
            end
            `OPC_JAL: begin
                imm = imm_j; result_sel = `RES_PC4;
                reg_write = 1'b1; is_jal = 1'b1;
            end
            `OPC_JALR: begin
                imm = imm_i; result_sel = `RES_PC4;
                reg_write = 1'b1; is_jalr = 1'b1;
            end
            `OPC_BRANCH: begin
                imm = imm_b; is_branch = 1'b1;
                alu_src_b = `B_RS2;   // comparison is on rs1 vs rs2
            end
            `OPC_LOAD: begin
                imm = imm_i; alu_op = `ALU_ADD; alu_src_b = `B_IMM;
                result_sel = `RES_MEM; reg_write = 1'b1; mem_read = 1'b1;
            end
            `OPC_STORE: begin
                imm = imm_s; alu_op = `ALU_ADD; alu_src_b = `B_IMM;
                mem_write = 1'b1;
            end
            `OPC_OPIMM: begin
                imm = imm_i; alu_op = alu_op_arith;
                alu_src_b = `B_IMM; reg_write = 1'b1;
            end
            `OPC_OP: begin
                alu_op = alu_op_arith;
                alu_src_b = `B_RS2; reg_write = 1'b1;
            end
            `OPC_MISCMEM: begin
                // FENCE / FENCE.I -> NOP on this single-hart in-order core.
            end
            `OPC_SYSTEM: begin
                // ECALL/EBREAK -> halt. (No CSRs implemented in base RV32I here.)
                is_halt = 1'b1;
            end
            default: begin
                // Unknown opcode: NOP (defaults already set).
            end
        endcase
    end
endmodule

`default_nettype wire

rtl/imem.v
// imem.v — synchronous-read instruction memory (infers BRAM).
// Word-addressed internally; `addr` is a byte address (PC). One-cycle read
// latency: address presented on cycle N, instruction valid on cycle N+1 —
// this IS the IF/ID pipeline register for the fetch stage.
// Unwritten locations default to NOP (addi x0,x0,0) so runaway fetch is safe.
`default_nettype none

module imem #(
    parameter ADDR_WIDTH = 12,          // words = 2^ADDR_WIDTH (default 4K words = 16KB)
    parameter INIT_FILE  = ""
)(
    input  wire        clk,
    input  wire        en,
    input  wire [31:0] addr,            // byte address
    output reg  [31:0] rdata
);
    localparam DEPTH = (1 << ADDR_WIDTH);
    (* ram_style = "block" *)
    reg [31:0] mem [0:DEPTH-1];

    wire [ADDR_WIDTH-1:0] widx = addr[ADDR_WIDTH+1:2];

    integer i;
    initial begin
        for (i = 0; i < DEPTH; i = i + 1)
            mem[i] = 32'h0000_0013;      // NOP
        if (INIT_FILE != "")
            $readmemh(INIT_FILE, mem);
    end

    always @(posedge clk) begin
        if (en)
            rdata <= mem[widx];
    end
endmodule

`default_nettype wire

rtl/rv32i_core.v
// rv32i_core.v — 3-stage pipelined RV32I core.
//
// Pipeline stages:
//   IF     : PC register drives synchronous imem; instruction appears next cycle.
//   ID/EX  : decode, regfile read (+WB->EX forwarding), ALU, branch/jump
//            resolution, and memory address/store formatting.
//   MEM/WB : capture synchronous dmem read data, format loads, select and
//            write back the result.
//
// Hazards:
//   Data    : a single WB->EX forwarding path. In a 3-stage pipeline the only
//             RAW distance that races the regfile is 1 (producer in WB while
//             consumer is in EX); distance >=2 is already committed and read
//             normally. Load data is a registered dmem output, stable through
//             the whole MEM/WB cycle, so loads forward with NO stall.
//   Control : branch/jump resolved in EX -> exactly one shadow instruction is
//             squashed (1-cycle penalty), and PC is redirected.
//
// I/O: a memory-mapped 16-bit output register (LED_ADDR) drives board LEDs;
//      ECALL/EBREAK halts the core (freezes PC, squashes the pipeline).
`include "rv32i_defs.vh"
`default_nettype none

module rv32i_core #(
    parameter IMEM_AW   = 12,
    parameter DMEM_AW   = 12,
    parameter IMEM_INIT = "",
    parameter DMEM_INIT = "",
    parameter [31:0] RESET_PC = 32'h0000_0000,
    parameter [31:0] LED_ADDR = 32'h0000_1000
)(
    input  wire        clk,
    input  wire        rst_n,       // synchronous, active-low
    output reg  [15:0] led,
    output reg         halted
);
    // ======================= IF stage =======================
    reg  [31:0] pc;
    wire [31:0] pc_plus4 = pc + 32'd4;
    wire [31:0] instr;               // registered imem output (this cycle's EX instr)

    imem #(.ADDR_WIDTH(IMEM_AW), .INIT_FILE(IMEM_INIT)) u_imem (
        .clk(clk), .en(1'b1), .addr(pc), .rdata(instr)
    );

    // id_pc: PC value that corresponds to `instr` currently in EX (PC delayed 1).
    reg [31:0] id_pc;

    // flush_ex: the instruction currently in EX is the shadow of a taken
    // branch/jump from the previous cycle and must be squashed.
    reg flush_ex;

    // ======================= ID/EX stage =======================
    wire [4:0]  rs1, rs2, rd;
    wire [2:0]  funct3;
    wire [31:0] imm;
    wire [3:0]  alu_op;
    wire        alu_src_a, alu_src_b;
    wire [1:0]  result_sel;
    wire        reg_write, mem_read, mem_write, is_branch, is_jal, is_jalr, is_halt;

    decoder u_decoder (
        .instr(instr),
        .rs1(rs1), .rs2(rs2), .rd(rd), .funct3(funct3),
        .imm(imm), .alu_op(alu_op), .alu_src_a(alu_src_a), .alu_src_b(alu_src_b),
        .result_sel(result_sel), .reg_write(reg_write),
        .mem_read(mem_read), .mem_write(mem_write),
        .is_branch(is_branch), .is_jal(is_jal), .is_jalr(is_jalr), .is_halt(is_halt)
    );

    // Squash EX when it holds a branch shadow, or once the core is halted.
    wire squash = flush_ex || halted;

    // ---- register file (write port lives in MEM/WB, below) ----
    wire [31:0] rs1_data, rs2_data;
    // WB-stage write signals (declared here, driven in MEM/WB section)
    wire        wb_reg_write;
    wire [4:0]  wb_rd;
    wire [31:0] wb_data;

    regfile u_regfile (
        .clk(clk),
        .rs1_addr(rs1), .rs1_data(rs1_data),
        .rs2_addr(rs2), .rs2_data(rs2_data),
        .we(wb_reg_write), .rd_addr(wb_rd), .rd_data(wb_data)
    );

    // ---- WB->EX forwarding ----
    wire fwd_a = wb_reg_write && (wb_rd != 5'd0) && (wb_rd == rs1);
    wire fwd_b = wb_reg_write && (wb_rd != 5'd0) && (wb_rd == rs2);
    wire [31:0] rs1_fwd = fwd_a ? wb_data : rs1_data;
    wire [31:0] rs2_fwd = fwd_b ? wb_data : rs2_data;

    // ---- ALU ----
    wire [31:0] alu_a = (alu_src_a == `A_PC)  ? id_pc  : rs1_fwd;
    wire [31:0] alu_b = (alu_src_b == `B_IMM) ? imm    : rs2_fwd;
    wire [31:0] alu_y;
    alu u_alu (.a(alu_a), .b(alu_b), .op(alu_op), .y(alu_y), .zero());

    // ---- branch condition ----
    reg branch_cond;
    always @(*) begin
        case (funct3)
            `F3_BEQ : branch_cond = (rs1_fwd == rs2_fwd);
            `F3_BNE : branch_cond = (rs1_fwd != rs2_fwd);
            `F3_BLT : branch_cond = ($signed(rs1_fwd) <  $signed(rs2_fwd));
            `F3_BGE : branch_cond = ($signed(rs1_fwd) >= $signed(rs2_fwd));
            `F3_BLTU: branch_cond = (rs1_fwd <  rs2_fwd);
            `F3_BGEU: branch_cond = (rs1_fwd >= rs2_fwd);
            default : branch_cond = 1'b0;
        endcase
    end

    wire take_branch = is_branch && branch_cond;
    wire redirect    = (~squash) && (take_branch || is_jal || is_jalr);

    wire [31:0] jalr_target   = (rs1_fwd + imm) & 32'hFFFF_FFFE;
    wire [31:0] pcrel_target  = id_pc + imm;             // branch / JAL
    wire [31:0] redirect_target = is_jalr ? jalr_target : pcrel_target;

    // ---- data memory address + store formatting (EX drives dmem) ----
    wire [31:0] mem_addr = alu_y;
    wire [1:0]  byte_off = mem_addr[1:0];
    wire        is_led   = (mem_addr == LED_ADDR);

    // Replicate store data across lanes; byte-enables pick the target lane(s).
    reg  [3:0]  store_be;
    reg  [31:0] store_wdata;
    always @(*) begin
        store_be    = 4'b0000;
        store_wdata = rs2_fwd;
        case (funct3)
            `F3_B: begin
                store_wdata = {4{rs2_fwd[7:0]}};
                store_be    = 4'b0001 << byte_off;
            end
            `F3_H: begin
                store_wdata = {2{rs2_fwd[15:0]}};
                store_be    = byte_off[1] ? 4'b1100 : 4'b0011;
            end
            `F3_W: begin
                store_wdata = rs2_fwd;
                store_be    = 4'b1111;
            end
            default: begin
                store_wdata = rs2_fwd;
                store_be    = 4'b1111;
            end
        endcase
    end

    // Effective control after squash/halt gating.
    wire do_reg_write = reg_write && ~squash;
    wire do_mem_write = mem_write && ~squash;
    wire [3:0] dmem_be = (do_mem_write && ~is_led) ? store_be : 4'b0000;

    wire [31:0] dmem_rdata;
    dmem #(.ADDR_WIDTH(DMEM_AW), .INIT_FILE(DMEM_INIT)) u_dmem (
        .clk(clk), .en(1'b1), .we(dmem_be),
        .addr(mem_addr), .wdata(store_wdata), .rdata(dmem_rdata)
    );

    // ======================= MEM/WB pipeline register =======================
    reg        wb_reg_write_r;
    reg [4:0]  wb_rd_r;
    reg [1:0]  wb_result_sel_r;
    reg [31:0] wb_alu_result_r;
    reg [31:0] wb_pc4_r;
    reg [2:0]  wb_funct3_r;
    reg [1:0]  wb_byteoff_r;

    // ======================= sequential state =======================
    wire halted_next = halted || (is_halt && ~squash);

    always @(posedge clk) begin
        if (!rst_n) begin
            pc              <= RESET_PC;
            id_pc           <= 32'd0;
            flush_ex        <= 1'b0;
            halted          <= 1'b0;
            led             <= 16'd0;
            wb_reg_write_r  <= 1'b0;
            wb_rd_r         <= 5'd0;
            wb_result_sel_r <= `RES_ALU;
            wb_alu_result_r <= 32'd0;
            wb_pc4_r        <= 32'd0;
            wb_funct3_r     <= 3'd0;
            wb_byteoff_r    <= 2'd0;
        end else begin
            // PC update
            if (halted_next)      pc <= pc;
            else if (redirect)    pc <= redirect_target;
            else                  pc <= pc_plus4;

            id_pc    <= pc;
            flush_ex <= redirect;          // next cycle's EX instr is the shadow
            halted   <= halted_next;

            // memory-mapped LED write
            if (do_mem_write && is_led)
                led <= store_wdata[15:0];

            // latch EX results into MEM/WB
            wb_reg_write_r  <= do_reg_write;
            wb_rd_r         <= rd;
            wb_result_sel_r <= result_sel;
            wb_alu_result_r <= alu_y;
            wb_pc4_r        <= id_pc + 32'd4;
            wb_funct3_r     <= funct3;
            wb_byteoff_r    <= byte_off;
        end
    end

    // ======================= MEM/WB combinational =======================
    // Load extraction/extension from the (registered) dmem word.
    reg [31:0] load_ext;
    reg [7:0]  lb;
    reg [15:0] lh;
    always @(*) begin
        lb = dmem_rdata[8*wb_byteoff_r +: 8];
        lh = wb_byteoff_r[1] ? dmem_rdata[31:16] : dmem_rdata[15:0];
        case (wb_funct3_r)
            `F3_B:  load_ext = {{24{lb[7]}},  lb};      // LB
            `F3_H:  load_ext = {{16{lh[15]}}, lh};      // LH
            `F3_W:  load_ext = dmem_rdata;              // LW
            `F3_BU: load_ext = {24'd0, lb};             // LBU
            `F3_HU: load_ext = {16'd0, lh};             // LHU
            default: load_ext = dmem_rdata;
        endcase
    end

    reg [31:0] wb_data_r;
    always @(*) begin
        case (wb_result_sel_r)
            `RES_MEM: wb_data_r = load_ext;
            `RES_PC4: wb_data_r = wb_pc4_r;
            default : wb_data_r = wb_alu_result_r;
        endcase
    end

    assign wb_reg_write = wb_reg_write_r;
    assign wb_rd        = wb_rd_r;
    assign wb_data      = wb_data_r;

endmodule

`default_nettype wire

sim/tb_wave.v
// tb_wave.v — runs a short program and dumps a VCD of the key pipeline signals,
// for turning into a waveform figure (scripts/vcd2svg.py). Not a pass/fail test.
`timescale 1ns/1ps

module tb_wave;
    reg clk = 0, rst_n = 0;
    wire [15:0] led;
    wire        halted;

    rv32i_core #(.LED_ADDR(32'h0000_1000)) dut (
        .clk(clk), .rst_n(rst_n), .led(led), .halted(halted)
    );

    always #5 clk = ~clk;   // 10 ns period

    integer cyc = 0;
    reg [8*256-1:0] hexfile;

    initial begin
        if (!$value$plusargs("HEX=%s", hexfile)) hexfile = "program.hex";
        #1; $readmemh(hexfile, dut.u_imem.mem);

        // Dump only the interesting scalars/buses (not the memory arrays).
        $dumpfile("wave.vcd");
        $dumpvars(0, clk, rst_n);
        $dumpvars(0, dut.pc, dut.id_pc, dut.instr,
                     dut.alu_a, dut.alu_b, dut.alu_y,
                     dut.redirect, dut.flush_ex,
                     dut.wb_reg_write, dut.wb_rd, dut.wb_data,
                     dut.halted, dut.led);

        rst_n = 0; repeat (3) @(posedge clk); rst_n = 1;
    end

    always @(posedge clk) begin
        if (rst_n) cyc = cyc + 1;
        if (halted || cyc > 40) begin
            @(posedge clk);
            $display("wavedemo done: cyc=%0d led=0x%h", cyc, led);
            $finish;
        end
    end
endmodule

sim/waves/wavedemo.vcd
$date
   Thu Aug 20 15:17:18 2026
$end
$version
  2020.2
$end
$timescale
  1ps
$end
$scope module tb_wave $end
$var reg 1 ! clk $end
$var reg 1 " rst_n $end
$scope module dut $end
$var reg 16 / led [15:0] $end
$var reg 1 . halted $end
$var reg 32 # pc [31:0] $end
$var wire 32 % instr [31:0] $end
$var reg 32 $ id_pc [31:0] $end
$var reg 1 * flush_ex $end
$var wire 1 + wb_reg_write $end
$var wire 5 , wb_rd [4:0] $end
$var wire 32 - wb_data [31:0] $end
$var wire 32 & alu_a [31:0] $end
$var wire 32 ' alu_b [31:0] $end
$var wire 32 ( alu_y [31:0] $end
$var wire 1 ) redirect $end
$upscope $end
$upscope $end
$enddefinitions $end
#0
$dumpvars
0!
0"
bx #
bx $
bx %
bx &
b0 '
bx (
0)
x*
x+
bx ,
bx -
x.
bx /
$end
#5000
1!
b0 #
b0 $
bx &
0)
0*
0+
b0 ,
b0 -
0.
b0 /
#10000
0!
#15000
1!
b0 #
b0 $
b10100000000001010010011 %
b0 &
b101 '
b101 (
0*
0.
b0 /
#20000
0!
#25000
1!
1"
b100 #
b0 $
b101 '
0*
1+
b101 ,
b101 -
0.
#30000
0!
#35000
1!
b1000 #
b100 $
b1100101000001100010011 %
b101 &
b11 '
b1000 (
0*
0.
#40000
0!
#45000
1!
b1100 #
b1000 $
b100000000000001110010011 %
b0 &
b1000 '
b1000 (
0*
b110 ,
b1000 -
0.
#50000
0!
#55000
1!
b10000 #
b1100 $
b11100110000010001100011 %
b1000 &
b1000 '
b10000 (
1)
0*
b111 ,
0.
#60000
0!
#65000
1!
b10100 #
b10000 $
b110001100000000111000010011 %
b0 &
b1100011 '
b1100011 (
0)
1*
0+
b1000 ,
b10000 -
0.
#70000
0!
#75000
1!
b11000 #
b10100 $
b11100000000111000010011 %
b0 &
b111 '
b111 (
0)
0*
b11100 ,
b1100011 -
0.
#80000
0!
#85000
1!
b11100 #
b11000 $
b1010010110111 %
b0 &
b1000000000000 '
b1000000000000 (
0*
1+
b111 -
0.
#90000
0!
#95000
1!
b100000 #
b11100 $
b1001000010010010011 %
b1000000000000 &
b0 '
0*
b1001 ,
b1000000000000 -
0.
#100000
0!
#105000
1!
b100100 #
b100000 $
b1110001001010000000100011 %
b1000000000000 &
b0 '
0*
0.
#110000
0!
#115000
1!
b101000 #
b100100 $
b1110011 %
b0 &
b0 '
b0 (
0*
0+
b0 ,
0.
b111 /
#120000
0!
#125000
1!
b101000 #
b101000 $
b10011 %
b0 &
0)
0*
b0 -
1.
#130000
0!
#135000
1!
b101000 #
b101000 $
0*
1.
